soco_tokenizer/__init__.py
soco_tokenizer/bert_tokenizer.py
soco_tokenizer/cloud_bucket.py
soco_tokenizer/config.py
soco_tokenizer/logging_handlerr.py
soco_tokenizer/model_loaders.py
soco_tokenizer/tokenizer.py
soco_tokenizer/util.py
soco_tokenizer-1.2.dist-info/LICENSE
soco_tokenizer-1.2.dist-info/METADATA
soco_tokenizer-1.2.dist-info/WHEEL
soco_tokenizer-1.2.dist-info/top_level.txt
soco_tokenizer-1.2.dist-info/RECORD
