Metadata-Version: 2.1
Name: soco-tokenizer
Version: 1.2
Summary: Fast tokenizer
Home-page: https://www.soco.ai
Author: tianchez
License: UNKNOWN
Platform: UNKNOWN
Classifier: Programming Language :: Python :: 3
Classifier: License :: Free for non-commercial use
Classifier: Operating System :: OS Independent
Requires-Dist: numpy (>=1.15.3)
Requires-Dist: boto3 (>=1.9.46)
Requires-Dist: oss2 (>=2.6.0)
Requires-Dist: tqdm (>=4.45.0)
Requires-Dist: nltk (>=3.5)
Requires-Dist: jieba-fast (>=0.53)
Requires-Dist: spacy (>=2.2.4)
Requires-Dist: requests (>=2.23.0)
Requires-Dist: tokenizers (>=0.7.0)
